tests/__init__.py
tests/test_utils.py
tuttusa_utils/__init__.py
tuttusa_utils/cli.py
tuttusa_utils/tuttusa_utils.py
tuttusa_utils-0.1.dist-info/AUTHORS.md
tuttusa_utils-0.1.dist-info/LICENSE
tuttusa_utils-0.1.dist-info/METADATA
tuttusa_utils-0.1.dist-info/WHEEL
tuttusa_utils-0.1.dist-info/top_level.txt
tuttusa_utils-0.1.dist-info/RECORD
