Metadata-Version: 2.1
Name: tuttusa-utils
Version: 0.1
Summary: Tuttusa Utils
Home-page: https://github.com/Tuttusa/tuttusa-utils
Author: Ashish
Author-email: agarwal.ashish.singhal@gmail.com
License: MIT
Download-URL: https://github.com/Tuttusa/tuttusa-utils/archive/v_01.tar.gz
Keywords: utils,pypi,Tuttusa
Platform: UNKNOWN
Classifier: Development Status :: 3 - Alpha
Classifier: Intended Audience :: Developers
Classifier: Topic :: Software Development :: Build Tools
Classifier: License :: OSI Approved :: MIT License
Classifier: Programming Language :: Python :: 3
Classifier: Programming Language :: Python :: 3.7
Classifier: Programming Language :: Python :: 3.8
Classifier: Programming Language :: Python :: 3.9
Requires-Dist: fire
Requires-Dist: tqdm
Requires-Dist: google-cloud-storage
Requires-Dist: sklearn
Requires-Dist: boto3
Requires-Dist: dload
Requires-Dist: requests
